CHANGES.txt
CONTRIBUTORS.txt
README.txt
bootstrap.py
buildout.cfg
setup.py
zopeskel.txt
collective/__init__.py
collective.recipe.zcml.egg-info/PKG-INFO
collective.recipe.zcml.egg-info/SOURCES.txt
collective.recipe.zcml.egg-info/dependency_links.txt
collective.recipe.zcml.egg-info/entry_points.txt
collective.recipe.zcml.egg-info/namespace_packages.txt
collective.recipe.zcml.egg-info/not-zip-safe
collective.recipe.zcml.egg-info/paster_plugins.txt
collective.recipe.zcml.egg-info/requires.txt
collective.recipe.zcml.egg-info/top_level.txt
collective/recipe/__init__.py
collective/recipe/zcml/README.txt
collective/recipe/zcml/__init__.py
collective/recipe/zcml/tests/__init__.py
collective/recipe/zcml/tests/test_docs.py