Metadata-Version: 1.0
Name: collective.recipe.zcml
Version: 0.1
Summary: ZCML slug generation to be used separately e.g for repoze based setups
Home-page:  https://svn.plone.org/svn/collective/buildout/collective.recipe.zcml/trunk
Author: Stefan Eletzhofer
Author-email: stefan.eletzhofer (at) inquant.de
License: ZPL
Platform: UNKNOWN
Classifier: Framework :: Buildout
Classifier: Intended Audience :: Developers
Classifier: Topic :: Software Development :: Build Tools
Classifier: Topic :: Software Development :: Libraries :: Python Modules
Classifier: License :: OSI Approved :: Zope Public License
